LICENSE
README.md
pyproject.toml
openet/__init__.py
openet/nrt/__init__.py
openet/nrt/image.py
openet/nrt/lst.py
openet/nrt/tasumi.py
openet/nrt/utils.py
openet/nrt/remove/landsat.py
openet/nrt/tests/conftest.py
openet/nrt/tests/test_image.py
openet/nrt/tests/test_lst.py
openet/nrt/tests/test_tasumi.py
openet_landsat_nrt.egg-info/PKG-INFO
openet_landsat_nrt.egg-info/SOURCES.txt
openet_landsat_nrt.egg-info/dependency_links.txt
openet_landsat_nrt.egg-info/requires.txt
openet_landsat_nrt.egg-info/top_level.txt